as_seg/CBM_algorithm.py
as_seg/__init__.py
as_seg/autosimilarity_computation.py
as_seg/barwise_input.py
as_seg/data_manipulation.py
as_seg/example.py
as_seg/foote_novelty.py
as_seg/model/__init__.py
as_seg/model/common_plot.py
as_seg/model/dataloaders.py
as_seg/model/errors.py
as_seg/model/signal_to_spectrogram.py
as_seg/scripts/__init__.py
as_seg/scripts/default_path.py
as_seg/scripts/display_results.py
as_seg/scripts/overall_scripts.py
as_seg-0.1.11.dist-info/AUTHORS
as_seg-0.1.11.dist-info/LICENSE.md
as_seg-0.1.11.dist-info/METADATA
as_seg-0.1.11.dist-info/WHEEL
as_seg-0.1.11.dist-info/top_level.txt
as_seg-0.1.11.dist-info/RECORD
