Metadata-Version: 2.1
Name: as_seg
Version: 0.1.11
Summary: Package for the segmentation of autosimilarity matrices. This version is related to a stable vesion on PyPi, for installation in MSAF.
Home-page: https://gitlab.imt-atlantique.fr/a23marmo/autosimilarity_segmentation
Author: Marmoret Axel
Author-email: axel.marmoret@imt-atlantique.fr
License: BSD
Classifier: License :: OSI Approved :: BSD License
Classifier: Programming Language :: Python
Classifier: Development Status :: 3 - Alpha
Classifier: Intended Audience :: Developers
Classifier: Intended Audience :: Science/Research
Classifier: Topic :: Multimedia :: Sound/Audio :: Analysis
Classifier: Programming Language :: Python :: 3.8
License-File: LICENSE.md
License-File: AUTHORS
Requires-Dist: base_audio
Requires-Dist: librosa>=0.10
Requires-Dist: madmom
Requires-Dist: matplotlib>=1.5
Requires-Dist: mir_eval
Requires-Dist: mirdata>=0.3.3
Requires-Dist: smart_open
Requires-Dist: numpy>=1.8.0
Requires-Dist: pandas
Requires-Dist: scikit-learn>=0.17.0
Requires-Dist: scipy>=0.13.0
Requires-Dist: tensorly>=0.5.1
Requires-Dist: IPython
